<?xml version="1.0"?>
<surround with="index.html" at="here">
 <h2> Getting Started </h2>
<div class="imp">
<ul>
  <li><a href="http://localhost:8080/features">Features</a></li>
  <li><a href="http://localhost:8080/anatomy">Anatomy of Our framework </a></li>
  <li><a href="http://localhost:8080/ide">Setting-up your preferred IDE </a></li>
   <li><a href="http://localhost:8080/createApp">Creating New Application </a></li>
  <li><a href="http://localhost:8080/sampleApp">Sample applications </a></li>
</ul>
</div>			
</surround>
